{
  "run_flags": {
    "CONDUCT_DATA_EXTRACTION": true,
    "CONDUCT_REPORT_GENERATION": true
  },
  "prn_files_folderpath": "source_files/prn_reports",
  "prn_files_data_extraction_config": { 
    "files_to_process": [
      {
        "alias": "2024",
        "filename": "Y2024_STOPS.PRN",
        "is_full_folderpath": false
      },
      {
        "alias": "2050",
        "filename": "Y2050_STOPS.PRN",
        "is_full_folderpath": false
      },
      {
        "alias": "brstops_skims_1_type0",
        "filename": "brstops_skims_1_type0.prn",
        "is_full_folderpath": true,
        "folderpath":"J:\\Shared drives\\TMD_TSA\\Projects\\STOPS\\Scenarios\\ModelVersion-0.2-UpdateScenarios\\[skim_update_scenarios]\\brstops_skims_1_type0\\Reports"
      },
      {
        "alias": "brstops_skims_2_type0",
        "filename": "brstops_skims_2_type0.prn",
        "is_full_folderpath": true,
        "folderpath":"J:\\Shared drives\\TMD_TSA\\Projects\\STOPS\\Scenarios\\ModelVersion-0.2-UpdateScenarios\\[skim_update_scenarios]\\brstops_skims_2_type0\\Reports"
      }
    ],
    "tables_to_extract": [
      {
        "table_name": "9.01",
        "method_name": "extract_table_9_01"
      },
      {
        "table_name": "10.01",
        "method_name": "extract_table_10_01"
      },
      {
        "table_name": "11.01",
        "method_name": "extract_table_11_01"
      }
    ],
  },
  "csv_output_folderpath": "extracted_csv_tables",
  "report_output_folderpath": "summary_report",
  
  "report_generation_data_config": {
    "route_level_comparison": {
        [
            "output_csv_name": "rapid_transit_comparison_output.csv",
            "table": 10.01,
            "rows": [
                "Blue&T", "Green-B&T", "Green-C&T", "Green-D&T", "Green-E&T",
            "Mattapan&T", "Orange&T", "Red&T"
            ]
            ],
        [
            "output_csv_name": "commuter_rail_comparison_output.csv",
            "table": 10.01,
            "rows": [
 "CR-Fairmount&T", "CR-Fitchburg&T", "CR-Franklin&T", "CR-Greenbush&T",
        "CR-Haverhill&T", "CR-Kingston&T", "CR-Lowell&T", "CR-Middleborough&T",
        "CR-Needham&T", "CR-Newburyport&T", "CR-Providence&T", "CR-Worcester&T",
        "CR: FALL River&T"
            ]
            ]
        }
    }
}